Metadata-Version: 2.4
Name: hack4uLib
Version: 0.1.0
Summary: Una biblioteca para consultar cursos de la academia hack4u.
Home-page: https://hack4u.io
Author: Rodrigo Inzaurralde
Dynamic: author
Dynamic: description
Dynamic: description-content-type
Dynamic: home-page
Dynamic: summary
